funcnodes_react_flow/__init__.py
funcnodes_react_flow/__main__.py
funcnodes_react_flow/plugin_setup.py
funcnodes_react_flow/run.py
funcnodes_react_flow/static/android-chrome-192x192.png
funcnodes_react_flow/static/android-chrome-512x512.png
funcnodes_react_flow/static/apple-touch-icon.png
funcnodes_react_flow/static/asset-manifest.json
funcnodes_react_flow/static/favicon-16x16.png
funcnodes_react_flow/static/favicon-32x32.png
funcnodes_react_flow/static/favicon.ico
funcnodes_react_flow/static/funcnodes_react_flow-favicon.ico
funcnodes_react_flow/static/funcnodes_react_flow-logo192.png
funcnodes_react_flow/static/funcnodes_react_flow-manifest.json
funcnodes_react_flow/static/funcnodes_react_flow-style.css
funcnodes_react_flow/static/funcnodes_react_flow.css
funcnodes_react_flow/static/funcnodes_react_flow.es.js
funcnodes_react_flow/static/funcnodes_react_flow.iife.js
funcnodes_react_flow/static/index.html
funcnodes_react_flow/static/logo.png
funcnodes_react_flow/static/logo192.png
funcnodes_react_flow/static/logo512.png
funcnodes_react_flow/static/manifest.json
funcnodes_react_flow/static/robots.txt
funcnodes_react_flow-2.2.1.dist-info/METADATA
funcnodes_react_flow-2.2.1.dist-info/WHEEL
funcnodes_react_flow-2.2.1.dist-info/entry_points.txt
funcnodes_react_flow-2.2.1.dist-info/licenses/LICENSE
funcnodes_react_flow-2.2.1.dist-info/RECORD
