Metadata-Version: 2.4
Name: funcnodes-react-flow
Version: 2.2.1
Summary: funcnodes frontend for react flow
Project-URL: homepage, https://github.com/Linkdlab/funcnodes_react_flow
Project-URL: source, https://github.com/Linkdlab/funcnodes_react_flow
Project-URL: tracker, https://github.com/Linkdlab/funcnodes_react_flow/issues
Project-URL: download, https://pypi.org/project/funcnodes-react-flow/#files
Author-email: Julian Kimmig <julian.kimmig@linkdlab.de>
License: AGPL-3.0
License-File: LICENSE
Classifier: License :: OSI Approved :: GNU Affero General Public License v3 or later (AGPLv3+)
Requires-Python: >=3.11
Requires-Dist: funcnodes-core>=1.0.0
Requires-Dist: funcnodes-worker>=1.0.0
Requires-Dist: funcnodes>=1.0.0
Requires-Dist: funcnodes>=1.0.0; sys_platform != 'emscripten'
